DatNTLibs/__init__.py
DatNTLibs/Datasets/__init__.py
DatNTLibs/Datasets/COCO/__init__.py
DatNTLibs/Datasets/COCO/main.py
DatNTLibs/KORLibs/Grammar.py
DatNTLibs/KORLibs/Vocad.py
DatNTLibs/KORLibs/__init__.py
DatNTLibs/PtLibs/__init__.py
DatNTLibs/PtLibs/datasets/__init__.py
DatNTLibs/PyLibs/Logs.py
DatNTLibs/PyLibs/__init__.py
DatNTLibs/PyLibs/Gits/CloneReposities.py
DatNTLibs/PyLibs/Gits/__init__.py
DatNTLibs/PyLibs/arguments/__init__.py
DatNTLibs/PyLibs/arguments/argument.py
DatNTLibs/PyLibs/datasets/BUSI.py
DatNTLibs/PyLibs/datasets/__init__.py
DatNTLibs/PyLibs/downloads/__init__.py
DatNTLibs/PyLibs/downloads/downloaders.py
DatNTLibs/PyLibs/images/ImageUtils.py
DatNTLibs/PyLibs/images/__init__.py
DatNTLibs/TFLibs/__init__.py
DatNTLibs/TFLibs/CustomLayers/RepConv.py
DatNTLibs/TFLibs/CustomLayers/SPP.py
DatNTLibs/TFLibs/CustomLayers/__init__.py
DatNTLibs/TFLibs/datasets/ClassificationDataset.py
DatNTLibs/TFLibs/datasets/DetectionDataset.py
DatNTLibs/TFLibs/datasets/SegmentationDataset.py
DatNTLibs/TFLibs/datasets/TFRecordDB.py
DatNTLibs/TFLibs/datasets/__init__.py
DatNTLib-0.0.3.dist-info/LICENSE
DatNTLib-0.0.3.dist-info/METADATA
DatNTLib-0.0.3.dist-info/WHEEL
DatNTLib-0.0.3.dist-info/top_level.txt
DatNTLib-0.0.3.dist-info/RECORD
