Metadata-Version: 2.1
Name: DatNTLib
Version: 0.0.3
Summary: Library package
Author-email: datnt <datdtbkhn.nguyen@gmail.com>
Classifier: Programming Language :: Python :: 3
Classifier: License :: OSI Approved :: MIT License
Classifier: Operating System :: OS Independent
Requires-Python: >=3.8
License-File: LICENSE
